deep_diff/__init__.py
deep_diff-0.0.4.dist-info/METADATA
deep_diff-0.0.4.dist-info/WHEEL
deep_diff-0.0.4.dist-info/top_level.txt
deep_diff-0.0.4.dist-info/RECORD
