Metadata-Version: 2.1
Name: deep-diff
Version: 0.0.4
Summary: a tool to diff dict list set data
Home-page: https://github.com/ider-zh/diff
Author: ider
Author-email: 326737833@qq.com
License: BSD 3-Clause license
Platform: UNKNOWN
Classifier: Topic :: Software Development :: Libraries
Classifier: Programming Language :: Python :: 3
Classifier: Programming Language :: Python :: 3 :: Only
